grizzly_common/__init__.py
grizzly_common/__version__.py
grizzly_common/arguments.py
grizzly_common/dummy_pymqi.py
grizzly_common/exceptions.py
grizzly_common/py.typed
grizzly_common/queues.py
grizzly_common/text.py
grizzly_common/transformer.py
grizzly_common/utils.py
grizzly_common/azure/__init__.py
grizzly_common/azure/aad.py
grizzly_loadtester_common-0.1.1.dist-info/METADATA
grizzly_loadtester_common-0.1.1.dist-info/WHEEL
grizzly_loadtester_common-0.1.1.dist-info/RECORD
