Metadata-Version: 2.4
Name: grizzly-loadtester-common
Version: 0.1.1
Summary: Common functionality used in grizzly-loadtester packages
Author-email: biometria <opensource@biometria.se>
Maintainer-email: Mikael Göransson <github@mgor.se>
License-Expression: MIT
Keywords: behave,common,grizzly,load,loadtest,locust,performance,traffic generator
Classifier: Development Status :: 4 - Beta
Classifier: License :: OSI Approved :: MIT License
Classifier: Natural Language :: English
Classifier: Programming Language :: Python
Classifier: Programming Language :: Python :: 3 :: Only
Classifier: Programming Language :: Python :: 3.10
Classifier: Programming Language :: Python :: 3.11
Classifier: Programming Language :: Python :: 3.12
Classifier: Programming Language :: Python :: 3.13
Classifier: Programming Language :: Python :: Implementation :: CPython
Requires-Python: >=3.10
Requires-Dist: azure-core>=1.35.0
Requires-Dist: behave>=1.3.1
Requires-Dist: jinja2-simple-tags>=0.6.1
Requires-Dist: jinja2>=3.1.6
Requires-Dist: jsonpath-ng>=1.7.0
Requires-Dist: lxml>=6.0.1
Requires-Dist: pyotp>=2.9.0
Requires-Dist: python-dateutil>=2.9.0.post0
Requires-Dist: pyyaml>=6.0.2
Requires-Dist: tzdata>=2025.2
